bpss_file_store_python/__init__.py
bpss_file_store_python/file_store.py
bpss_file_store_python/lib/__init__.py
bpss_file_store_python/lib/aws.py
bpss_file_store_python/lib/azure.py
bpss_file_store_python/lib/constant.py
bpss_file_store_python/lib/gcp.py
bpss_file_store_python-1.3.2.dist-info/METADATA
bpss_file_store_python-1.3.2.dist-info/WHEEL
bpss_file_store_python-1.3.2.dist-info/top_level.txt
bpss_file_store_python-1.3.2.dist-info/RECORD
