Metadata-Version: 2.4
Name: bpss_file_store_python
Version: 1.3.2
Requires-Dist: boto3==1.26.150
Requires-Dist: azure-storage-blob==12.16.0
Requires-Dist: google-cloud-storage==2.9.0
Dynamic: description
Dynamic: description-content-type
Dynamic: requires-dist
